weiyuan_mcp_demo/__init__.py
weiyuan_mcp_demo-0.1.0.dist-info/WHEEL
weiyuan_mcp_demo-0.1.0.dist-info/entry_points.txt
weiyuan_mcp_demo-0.1.0.dist-info/METADATA
weiyuan_mcp_demo-0.1.0.dist-info/RECORD
